sarx/__init__.py
sarx/activate.py
sarx/apply.py
sarx/compose.py
sarx/core/__init__.py
sarx/core/forward/__init__.py
sarx/core/forward/first.py
sarx/core/forward/forward.py
sarx/core/forward/tail.py
sarx/forward.py
sarx/gradient/__init__.py
sarx/gradient/descent.py
sarx/identity.py
sarx/loss.py
sarx/mse.py
sarx/network.py
sarx/neurogenesis/__init__.py
sarx/neurogenesis/insert.py
sarx/neurogenesis/left.py
sarx/neurogenesis/neurogenesis.py
sarx/neurogenesis/right.py
sarx/spike.py
sarx/synapse.py
sarx/update.py
sarx/vjp/__init__.py
sarx/vjp/clip.py
sarx/vjp/identity.py
sarx-0.6.0.dist-info/LICENSE
sarx-0.6.0.dist-info/METADATA
sarx-0.6.0.dist-info/WHEEL
sarx-0.6.0.dist-info/RECORD
