Metadata-Version: 2.1
Name: sarx
Version: 0.6.0
Summary: A simple bioinspired artificial neural network in JAX
Home-page: https://github.com/ivandustin/sarx
License: MIT
Author: Ivan Dustin Bilon
Author-email: ivan22.dust@gmail.com
Requires-Python: >=3.9,<4.0
Classifier: License :: OSI Approved :: MIT License
Classifier: Programming Language :: Python :: 3
Classifier: Programming Language :: Python :: 3.9
Classifier: Programming Language :: Python :: 3.10
Classifier: Programming Language :: Python :: 3.11
Requires-Dist: jax (>=0.4.4,<0.5.0)
Requires-Dist: jaxlib (>=0.4.4,<0.5.0)
Requires-Dist: multipledispatch (>=0.6.0,<0.7.0)
Project-URL: Repository, https://github.com/ivandustin/sarx
